package com.nianticproject.ingress.common.m;

import com.nianticproject.ingress.common.f.h;

final class b extends h
{
  b(a parama, String paramString1, String paramString2, d paramd, int paramInt)
  {
  }

  // ERROR //
  private java.lang.Void j()
  {
    // Byte code:
    //   0: ldc 34
    //   2: invokestatic 39	com/nianticproject/ingress/shared/aj:a	(Ljava/lang/String;)V
    //   5: aload_0
    //   6: getfield 17	com/nianticproject/ingress/common/m/b:e	Lcom/nianticproject/ingress/common/m/a;
    //   9: invokestatic 44	com/nianticproject/ingress/common/m/a:a	(Lcom/nianticproject/ingress/common/m/a;)Lcom/nianticproject/ingress/common/u/ah;
    //   12: astore 5
    //   14: aload_0
    //   15: getfield 19	com/nianticproject/ingress/common/m/b:a	Ljava/lang/String;
    //   18: astore 6
    //   20: aload_0
    //   21: getfield 21	com/nianticproject/ingress/common/m/b:b	Ljava/lang/String;
    //   24: invokestatic 49	com/google/a/a/br:b	(Ljava/lang/String;)Z
    //   27: ifne +63 -> 90
    //   30: aload_0
    //   31: getfield 21	com/nianticproject/ingress/common/m/b:b	Ljava/lang/String;
    //   34: astore 7
    //   36: aload 5
    //   38: aload 6
    //   40: aload 7
    //   42: invokestatic 54	com/nianticproject/ingress/common/u/aj:a	(Ljava/lang/String;Ljava/lang/String;)Lcom/nianticproject/ingress/shared/rpc/ab;
    //   45: invokevirtual 59	com/nianticproject/ingress/common/u/ah:a	(Lcom/nianticproject/ingress/shared/rpc/ab;)Lcom/nianticproject/ingress/shared/rpc/RpcResult;
    //   48: astore 8
    //   50: aload 8
    //   52: astore_3
    //   53: invokestatic 61	com/nianticproject/ingress/shared/aj:b	()V
    //   56: ldc 63
    //   58: invokestatic 39	com/nianticproject/ingress/shared/aj:a	(Ljava/lang/String;)V
    //   61: aload_3
    //   62: ifnonnull +50 -> 112
    //   65: aload_0
    //   66: getfield 23	com/nianticproject/ingress/common/m/b:c	Lcom/nianticproject/ingress/common/m/d;
    //   69: aload_0
    //   70: getfield 25	com/nianticproject/ingress/common/m/b:d	I
    //   73: aload_0
    //   74: getfield 19	com/nianticproject/ingress/common/m/b:a	Ljava/lang/String;
    //   77: getstatic 68	com/nianticproject/ingress/shared/rpc/o:e	Lcom/nianticproject/ingress/shared/rpc/o;
    //   80: invokeinterface 73 4 0
    //   85: invokestatic 61	com/nianticproject/ingress/shared/aj:b	()V
    //   88: aconst_null
    //   89: areturn
    //   90: ldc 75
    //   92: astore 7
    //   94: goto -58 -> 36
    //   97: astore_2
    //   98: invokestatic 61	com/nianticproject/ingress/shared/aj:b	()V
    //   101: aconst_null
    //   102: astore_3
    //   103: goto -47 -> 56
    //   106: astore_1
    //   107: invokestatic 61	com/nianticproject/ingress/shared/aj:b	()V
    //   110: aload_1
    //   111: athrow
    //   112: aload_3
    //   113: invokevirtual 80	com/nianticproject/ingress/shared/rpc/RpcResult:e	()Z
    //   116: ifeq +41 -> 157
    //   119: aload_0
    //   120: getfield 23	com/nianticproject/ingress/common/m/b:c	Lcom/nianticproject/ingress/common/m/d;
    //   123: aload_0
    //   124: getfield 25	com/nianticproject/ingress/common/m/b:d	I
    //   127: aload_0
    //   128: getfield 19	com/nianticproject/ingress/common/m/b:a	Ljava/lang/String;
    //   131: invokeinterface 83 3 0
    //   136: aload_0
    //   137: getfield 23	com/nianticproject/ingress/common/m/b:c	Lcom/nianticproject/ingress/common/m/d;
    //   140: aload_3
    //   141: invokevirtual 86	com/nianticproject/ingress/shared/rpc/RpcResult:a	()Ljava/lang/Object;
    //   144: checkcast 88	com/nianticproject/ingress/shared/invites/InviteInfo
    //   147: invokeinterface 91 2 0
    //   152: invokestatic 61	com/nianticproject/ingress/shared/aj:b	()V
    //   155: aconst_null
    //   156: areturn
    //   157: aload_0
    //   158: getfield 23	com/nianticproject/ingress/common/m/b:c	Lcom/nianticproject/ingress/common/m/d;
    //   161: aload_0
    //   162: getfield 25	com/nianticproject/ingress/common/m/b:d	I
    //   165: aload_0
    //   166: getfield 19	com/nianticproject/ingress/common/m/b:a	Ljava/lang/String;
    //   169: aload_3
    //   170: invokevirtual 93	com/nianticproject/ingress/shared/rpc/RpcResult:b	()Ljava/lang/Object;
    //   173: checkcast 65	com/nianticproject/ingress/shared/rpc/o
    //   176: invokeinterface 73 4 0
    //   181: goto -29 -> 152
    //   184: astore 4
    //   186: invokestatic 61	com/nianticproject/ingress/shared/aj:b	()V
    //   189: aload 4
    //   191: athrow
    //
    // Exception table:
    //   from	to	target	type
    //   0	36	97	com/nianticproject/ingress/shared/rpc/y
    //   36	50	97	com/nianticproject/ingress/shared/rpc/y
    //   0	36	106	finally
    //   36	50	106	finally
    //   56	61	184	finally
    //   65	85	184	finally
    //   112	152	184	finally
    //   157	181	184	finally
  }
}

/* Location:           classes_dex2jar.jar
 * Qualified Name:     com.nianticproject.ingress.common.m.b
 * JD-Core Version:    0.6.2
 */