package com.nianticproject.ingress.common.v;

import com.nianticproject.ingress.common.f.h;
import com.nianticproject.ingress.common.u.q;
import com.nianticproject.ingress.shared.ai;

final class f extends h
{
  f(e parame, q paramq, ai paramai)
  {
  }

  // ERROR //
  private java.lang.Void j()
  {
    // Byte code:
    //   0: ldc 27
    //   2: invokestatic 32	com/nianticproject/ingress/shared/aj:a	(Ljava/lang/String;)V
    //   5: aload_0
    //   6: getfield 16	com/nianticproject/ingress/common/v/f:a	Lcom/nianticproject/ingress/common/u/q;
    //   9: aload_0
    //   10: getfield 18	com/nianticproject/ingress/common/v/f:b	Lcom/nianticproject/ingress/shared/ai;
    //   13: invokestatic 37	com/nianticproject/ingress/common/u/aj:a	(Lcom/nianticproject/ingress/shared/ai;)Lcom/nianticproject/ingress/shared/rpc/ab;
    //   16: invokevirtual 42	com/nianticproject/ingress/common/u/q:b	(Lcom/nianticproject/ingress/shared/rpc/ab;)Ljava/lang/Object;
    //   19: pop
    //   20: aload_0
    //   21: getfield 14	com/nianticproject/ingress/common/v/f:c	Lcom/nianticproject/ingress/common/v/e;
    //   24: getfield 47	com/nianticproject/ingress/common/v/e:b	Lcom/nianticproject/ingress/common/r;
    //   27: invokevirtual 51	com/nianticproject/ingress/common/r:b	()V
    //   30: invokestatic 52	com/nianticproject/ingress/shared/aj:b	()V
    //   33: aconst_null
    //   34: areturn
    //   35: astore_1
    //   36: invokestatic 52	com/nianticproject/ingress/shared/aj:b	()V
    //   39: aload_1
    //   40: athrow
    //   41: astore_2
    //   42: goto -22 -> 20
    //
    // Exception table:
    //   from	to	target	type
    //   0	5	35	finally
    //   5	20	35	finally
    //   20	30	35	finally
    //   5	20	41	com/nianticproject/ingress/shared/rpc/y
  }
}

/* Location:           classes_dex2jar.jar
 * Qualified Name:     com.nianticproject.ingress.common.v.f
 * JD-Core Version:    0.6.2
 */