package com.nianticproject.ingress.l;

final class v
  implements Runnable
{
  v(u paramu, String paramString)
  {
  }

  // ERROR //
  public final void run()
  {
    // Byte code:
    //   0: aload_0
    //   1: getfield 14	com/nianticproject/ingress/l/v:b	Lcom/nianticproject/ingress/l/u;
    //   4: getfield 25	com/nianticproject/ingress/l/u:b	Lcom/nianticproject/ingress/l/f;
    //   7: invokestatic 30	com/nianticproject/ingress/l/f:b	(Lcom/nianticproject/ingress/l/f;)Ljava/util/EnumMap;
    //   10: astore_1
    //   11: aload_1
    //   12: monitorenter
    //   13: ldc 32
    //   15: aload_0
    //   16: getfield 16	com/nianticproject/ingress/l/v:a	Ljava/lang/String;
    //   19: ldc 34
    //   21: invokestatic 39	com/nianticproject/ingress/shared/aj:a	(Ljava/lang/String;Ljava/lang/String;Ljava/lang/String;)V
    //   24: aload_0
    //   25: getfield 14	com/nianticproject/ingress/l/v:b	Lcom/nianticproject/ingress/l/u;
    //   28: getfield 25	com/nianticproject/ingress/l/u:b	Lcom/nianticproject/ingress/l/f;
    //   31: invokestatic 30	com/nianticproject/ingress/l/f:b	(Lcom/nianticproject/ingress/l/f;)Ljava/util/EnumMap;
    //   34: aload_0
    //   35: getfield 16	com/nianticproject/ingress/l/v:a	Ljava/lang/String;
    //   38: invokevirtual 45	java/util/EnumMap:remove	(Ljava/lang/Object;)Ljava/lang/Object;
    //   41: pop
    //   42: invokestatic 47	com/nianticproject/ingress/shared/aj:b	()V
    //   45: aload_1
    //   46: monitorexit
    //   47: return
    //   48: astore_2
    //   49: invokestatic 47	com/nianticproject/ingress/shared/aj:b	()V
    //   52: aload_2
    //   53: athrow
    //   54: astore_3
    //   55: aload_1
    //   56: monitorexit
    //   57: aload_3
    //   58: athrow
    //
    // Exception table:
    //   from	to	target	type
    //   13	42	48	finally
    //   42	47	54	finally
    //   49	54	54	finally
  }
}

/* Location:           classes_dex2jar.jar
 * Qualified Name:     com.nianticproject.ingress.l.v
 * JD-Core Version:    0.6.2
 */