package com.nianticproject.ingress;

import com.nianticproject.ingress.common.f.h;
import com.nianticproject.ingress.gameentity.f;

final class af extends h
{
  af(ae paramae, f paramf)
  {
  }

  // ERROR //
  private java.lang.Void j()
  {
    // Byte code:
    //   0: ldc 23
    //   2: invokestatic 28	com/nianticproject/ingress/shared/aj:a	(Ljava/lang/String;)V
    //   5: aload_0
    //   6: getfield 14	com/nianticproject/ingress/af:a	Lcom/nianticproject/ingress/gameentity/f;
    //   9: invokeinterface 34 1 0
    //   14: invokestatic 39	com/nianticproject/ingress/common/u/aj:a	(Ljava/lang/String;)Lcom/nianticproject/ingress/shared/rpc/ab;
    //   17: astore_2
    //   18: aload_0
    //   19: getfield 12	com/nianticproject/ingress/af:b	Lcom/nianticproject/ingress/ae;
    //   22: invokestatic 44	com/nianticproject/ingress/ae:a	(Lcom/nianticproject/ingress/ae;)Lcom/nianticproject/ingress/common/u/q;
    //   25: aload_2
    //   26: invokevirtual 49	com/nianticproject/ingress/common/u/q:a	(Lcom/nianticproject/ingress/shared/rpc/ab;)Lcom/nianticproject/ingress/shared/rpc/RpcResult;
    //   29: pop
    //   30: invokestatic 51	com/nianticproject/ingress/shared/aj:b	()V
    //   33: aconst_null
    //   34: areturn
    //   35: astore_1
    //   36: invokestatic 51	com/nianticproject/ingress/shared/aj:b	()V
    //   39: aload_1
    //   40: athrow
    //   41: astore_3
    //   42: goto -12 -> 30
    //
    // Exception table:
    //   from	to	target	type
    //   0	18	35	finally
    //   18	30	35	finally
    //   18	30	41	com/nianticproject/ingress/shared/rpc/y
  }
}

/* Location:           classes_dex2jar.jar
 * Qualified Name:     com.nianticproject.ingress.af
 * JD-Core Version:    0.6.2
 */